webpartners_users/__init__.py
webpartners_users/admin.py
webpartners_users/models.py
webpartners_users/settings.py
webpartners_users/urls.py
webpartners_users/api/__init__.py
webpartners_users/api/permissions/__init__.py
webpartners_users/api/permissions/v1.py
webpartners_users/api/routers/__init__.py
webpartners_users/api/routers/v1.py
webpartners_users/api/serializers/__init__.py
webpartners_users/api/serializers/v1.py
webpartners_users/api/views/__init__.py
webpartners_users/api/views/v1.py
webpartners_users/migrations/0001_initial.py
webpartners_users/migrations/__init__.py
webpartners_users/tests/__init__.py
webpartners_users/tests/test_api_v1.py
webpartners_users/tests/test_jwt.py
webpartners_users-0.2.0.dist-info/METADATA
webpartners_users-0.2.0.dist-info/WHEEL
webpartners_users-0.2.0.dist-info/top_level.txt
webpartners_users-0.2.0.dist-info/RECORD
